cnc/__init__.py
cnc/check_dependencies.py
cnc/commands/__init__.py
cnc/commands/build.py
cnc/commands/deploy.py
cnc/commands/info.py
cnc/commands/provision.py
cnc/commands/render.py
cnc/commands/shell.py
cnc/commands/telemetry.py
cnc/commands/template_editor/__init__.py
cnc/commands/template_editor/inspector.py
cnc/commands/toolbox.py
cnc/commands/update.py
cnc/constants.py
cnc/flavors/aws/ecs/1/build/build_functions.sh.j2
cnc/flavors/aws/ecs/1/build/build_lambda_functions.sh.j2
cnc/flavors/aws/ecs/1/build/main.sh.j2
cnc/flavors/aws/ecs/1/deploy/base.sh.j2
cnc/flavors/aws/ecs/1/deploy/deploy_functions.sh.j2
cnc/flavors/aws/ecs/1/deploy/deploy_lambda_functions.sh.j2
cnc/flavors/aws/ecs/1/deploy/ecs_web_task.json.j2
cnc/flavors/aws/ecs/1/deploy/env_vars.json.j2
cnc/flavors/aws/ecs/1/deploy/main.sh.j2
cnc/flavors/aws/ecs/1/deploy/partials/backend_deploy.sh.j2
cnc/flavors/aws/ecs/1/deploy/partials/backend_deploy_status_check.sh.j2
cnc/flavors/aws/ecs/1/deploy/partials/ecs_wait_with_retries.sh.j2
cnc/flavors/aws/ecs/1/deploy/partials/update_task_definition.sh.j2
cnc/flavors/aws/ecs/1/deploy/pre_deploy.sh.j2
cnc/flavors/aws/ecs/1/deploy/pre_deploy_functions.sh.j2
cnc/flavors/aws/ecs/1/provision/base.tf.j2
cnc/flavors/aws/ecs/1/provision/frontend_routing_lambda/index.js
cnc/flavors/aws/ecs/1/provision/main.tf.j2
cnc/flavors/aws/ecs/1/provision/partials/collection/has_active_backend_deployments.tf.j2
cnc/flavors/aws/ecs/1/provision/partials/collection/has_active_deployments.tf.j2
cnc/flavors/aws/ecs/1/provision/partials/collection/has_active_frontend_deployments.tf.j2
cnc/flavors/aws/ecs/1/provision/partials/collection/has_backend_services.tf.j2
cnc/flavors/aws/ecs/1/provision/partials/collection/lambda/config_alb.tf.j2
cnc/flavors/aws/ecs/1/provision/partials/collection/vpc_configuration.tf.j2
cnc/flavors/aws/ecs/1/provision/partials/collection_level_resources.tf.j2
cnc/flavors/aws/ecs/1/provision/partials/environment/efs.tf.j2
cocnc-0.2.38.dist-info/METADATA
cocnc-0.2.38.dist-info/WHEEL
cocnc-0.2.38.dist-info/entry_points.txt
cocnc-0.2.38.dist-info/licenses/LICENSE.txt
cocnc-0.2.38.dist-info/RECORD
