Metadata-Version: 2.4
Name: cocnc
Version: 0.2.38
Summary: CNC is the first framework for application deployment, a fully distributed and customizable PaaS developer experience, based on docker-compose config files
License-File: LICENSE.txt
Author: Adam Abdelaziz
Author-email: adam.abdelaziz@withcoherence.com
Requires-Python: >=3.10,<4.0
Classifier: Programming Language :: Python :: 3
Classifier: Programming Language :: Python :: 3.10
Classifier: Programming Language :: Python :: 3.11
Classifier: Programming Language :: Python :: 3.12
Classifier: Programming Language :: Python :: 3.13
Classifier: Programming Language :: Python :: 3.14
Requires-Dist: boto3 (==1.38.39)
Requires-Dist: botocore (==1.38.39)
Requires-Dist: click (==8.1.8)
Requires-Dist: google-cloud-secret-manager (==2.24.0)
Requires-Dist: ipython (==8.37.0)
Requires-Dist: jinja2 (==3.1.6)
Requires-Dist: py-machineid (==0.5.1)
Requires-Dist: pydantic (==2.6.3)
Requires-Dist: pydantic-core (==2.16.3)
Requires-Dist: pygohcl (==1.2.5)
Requires-Dist: pyyaml (==6.0.2)
Requires-Dist: rich (==13.9.4)
Requires-Dist: rudder-sdk-python (==2.1.4)
Requires-Dist: shellingham (==1.5.4)
Requires-Dist: tabulate (==0.9.0)
Requires-Dist: toml (==0.10.2)
Requires-Dist: typer[all] (==0.9.4)
Requires-Dist: typing-extensions (==4.12.2)
Project-URL: Homepage, https://github.com/coherenceplatform/cnc
Project-URL: Repository, https://github.com/coherenceplatform/cnc
